{"security":[{"furkot_auth_access_code":["read:trips"]},{"furkot_auth_implicit":["read:trips"]}],"basePath":"/pub/api","paths":{"/trip/{trip_id}/stop":{"get":{"produces":["application/json"],"description":"list stops for a trip identified by {trip_id}","responses":{"200":{"schema":{"type":"array","items":{"$ref":"#/definitions/Step"}},"description":"Successful response"}},"parameters":[{"in":"path","name":"trip_id","description":"id of the trip","type":"string","required":true}]}},"/trip":{"get":{"produces":["application/json"],"description":"list user's trips","responses":{"200":{"schema":{"type":"array","items":{"$ref":"#/definitions/Trip"}},"description":"Successful response"}}}}},"host":"trips.furkot.com","schemes":["https"],"externalDocs":{"description":"Furkot API description","url":"https://help.furkot.com/widgets/furkot-api.html"},"definitions":{"Trip":{"type":"object","properties":{"name":{"description":"name of the trip","type":"string"},"description":{"description":"description of the trip (truncated to 200 characters)","type":"string"},"end":{"format":"date-time","description":"end of the trip in its local timezone as YYYY-MM-DDThh:mm","type":"string"},"id":{"description":"Unique ID of the trip","type":"string"},"begin":{"format":"date-time","description":"begin of the trip in its local timezone as YYYY-MM-DDThh:mm","type":"string"}}},"Step":{"type":"object","properties":{"address":{"description":"address of the stop","type":"string"},"route":{"description":"route leading to the stop","type":"object","properties":{"mode":{"description":"travel mode","type":"string","enum":["car","motorcycle","bicycle","walk","other"]},"duration":{"format":"int64","description":"route duration in seconds","type":"integer"},"distance":{"format":"int64","description":"route distance in meters","type":"integer"},"polyline":{"description":"route path compatible with Google polyline encoding algorithm","type":"string"}}},"arrival":{"format":"date-time","description":"arrival at the stop in its local timezone as YYYY-MM-DDThh:mm","type":"string"},"nights":{"format":"int64","description":"number of nights","type":"integer"},"name":{"description":"name of the stop","type":"string"},"coordinates":{"description":"geographical coordinates of the stop","type":"object","properties":{"lon":{"format":"float","description":"longitude","type":"number"},"lat":{"format":"float","description":"latitude","type":"number"}}},"departure":{"format":"date-time","description":"departure from the stop in its local timezone as YYYY-MM-DDThh:mm","type":"string"},"url":{"description":"url of the page with more information about the stop","type":"string"}}}},"securityDefinitions":{"furkot_auth_access_code":{"tokenUrl":"https://trips.furkot.com/pub/api/access_token","authorizationUrl":"https://trips.furkot.com/oauth/authorize","scopes":{"read:trips":"list trips and stops info"},"type":"oauth2","flow":"accessCode"},"furkot_auth_implicit":{"authorizationUrl":"https://trips.furkot.com/oauth/authorize","scopes":{"read:trips":"list users trips info"},"type":"oauth2","flow":"implicit"}},"swagger":"2.0","info":{"contact":{"email":"trips@furkot.com"},"description":"Furkot provides Rest API to access user trip data.\nUsing Furkot API an application can list user trips and display stops for a specific trip.\nFurkot API uses OAuth2 protocol to authorize applications to access data on behalf of users.\n","title":"Furkot Trips","version":"1.0.0"}}